{
  "products": {
    "sequence": 0,
    "products": {
      "type": "ProductTile",
      "product": [
        {
          "id": "0",
          "upc": "8056597874830",
          "brand": "Ray-Ban",
          "price": "449.00",
          "pdpURL": "https://www.opsm.com.au/ray-ban/rw4009-ray-ban-meta-headliner/8056597874830",
          "productName": "Ray-Ban Meta | Headliner",
          "productNameMOCO": "0RW4009__601_SB"
        },
        {
          "id": "1",
          "upc": "8056597988391",
          "brand": "Ray-Ban",
          "price": "489.00",
          "pdpURL": "https://www.opsm.com.au/ray-ban/rw4009-ray-ban-meta-headliner/8056597988391",
          "productName": "Ray-Ban Meta | Headliner",
          "productNameMOCO": "0RW4009__601_9A"
        },
        {
          "id": "2",
          "upc": "8056597982900",
          "brand": "Ray-Ban",
          "price": "449.00",
          "pdpURL": "https://www.opsm.com.au/ray-ban/rw4009-ray-ban-meta-headliner/8056597982900",
          "productName": "Ray-Ban Meta | Headliner",
          "productNameMOCO": "0RW4009__601S87"
        },
        {
          "id": "3",
          "upc": "8056597982894",
          "brand": "Ray-Ban",
          "price": "539.00",
          "pdpURL": "https://www.opsm.com.au/ray-ban/rw4009-ray-ban-meta-headliner/8056597982894",
          "productName": "Ray-Ban Meta | Headliner",
          "productNameMOCO": "0RW4009__601SM3"
        },
        {
          "id": "4",
          "upc": "8056262017005",
          "brand": "Ray-Ban",
          "price": "449.00",
          "pdpURL": "https://www.opsm.com.au/ray-ban/rw4009-ray-ban-meta-headliner/8056262017005",
          "productName": "Ray-Ban Meta | Headliner",
          "productNameMOCO": "0RW4009__670680"
        },
        {
          "id": "5",
          "upc": "8056597982887",
          "brand": "Ray-Ban",
          "price": "489.00",
          "pdpURL": "https://www.opsm.com.au/ray-ban/rw4009-ray-ban-meta-headliner/8056597982887",
          "productName": "Ray-Ban Meta | Headliner",
          "productNameMOCO": "0RW4009__66985Q"
        },
        {
          "id": "6",
          "upc": "8056597995436",
          "brand": "Ray-Ban",
          "price": "489.00",
          "pdpURL": "https://www.opsm.com.au/ray-ban/rw4009-ray-ban-meta-headliner/8056597995436",
          "productName": "Ray-Ban Meta | Headliner",
          "productNameMOCO": "0RW4009__675483"
        }
      ]
    }
  }
}
